{"updateAt":"2022-06-09T02:39:13.338Z","data":{"category":"競賽活動公告區","title":"「有BIM的世界長怎樣」","href":"http://www.smhs.kh.edu.tw/p/406-1000-3856,r21.php","date":"2022-06-07","external":false,"content":"<div><div></div><div>二、研習營相關資訊：<br> (一)研習日期：111年7月11、12日。<br> (二)研習地點：臺大BIM研究中心 （臺北市大安區辛亥路3段<br> 200號）。<br> (三)活動費用：新臺幣4,800元／人。<br> (四)活動人數：20名。<br> (五)報名期間：即日起至111年7月1日止。<br> (六)招生對象：對智慧建築、數位營建、資訊科技有興趣的<br> 高中職在學、應屆生。<br> (七)報名連結：www.accupass.com/go/bimsummer2022。<br> 三、活動洽詢：臺大BIM研究中心 02-33666572、02-<br> 33666573；Email：ntubimcenter@gmail.com。</div></div>","attachments":[]}}