{"updateAt":"2022-04-11T02:27:12.823Z","data":{"category":"升學公告區","title":"國立臺灣師範大學地球科學系於今(111)年5月14日(星期六)，假本校公館校區舉辦「Open House開放參觀日」","href":"http://www.smhs.kh.edu.tw/p/406-1000-3344,r20.php?Lang=zh-tw","date":"2022-04-06","external":false,"content":"<div><div></div><div></div></div>","attachments":[{"name":"附件.zip","href":"https://www.smhs.kh.edu.tw/app/index.php?Action=downloadfile&file=WVhSMFlXTm9MelEyTDNCMFlWOHpNVEEzWHpNeU1EUXlNVGhmTVRRd09UY3VlbWx3&fname=DGGGROTSYWQO41XX50LKSWHGRK30OOLKDGUWTSKK4125MLVWKPROVTPOUSSSPKPO"}]}}