{"updateAt":"2022-03-26T02:13:00.518Z","data":{"category":"公文公告區","title":"銘傳大學舉辦2022銘傳觀光國際研討會中、英文小論文競賽評選徵稿，請有興趣同學們踴躍參加。","href":"http://www.smhs.kh.edu.tw/p/406-1000-3213,r22.php","date":"2022-03-17","external":false,"content":"<div><div></div><div>一、2022觀光國際學術研討會中透過學術能力整合教育與社會服務的精神，<br> 協助高中職論文寫作的評選和意見回饋，達到108新課綱倡導的獨立思考<br> 、問題解決能力之目標，將邀請高中、職學生參與小論文競賽進行海報發表。<br> 二、發表時間:2022年4月15日(五)；地點:銘傳大學桃園校區。<br> 三、投稿截止日期:2022年3月30日(三)，投稿請寄至<br> tourismcu2022@gmail.com(主旨敘明:『高中職學生小論文競賽』)。<br> 四、審查結果於2022年04月05日(二)公告於『銘傳觀光研討會』FB 粉絲<br> 專頁(https://www.facebook.com/MCUTourismCon)，並email通知投稿人。<br> 五、中、英文小論文競賽評選辦法，詳見附件1。<br> 六、錄取作品出席發表者，請所屬學校准請公假處理。<br> 七、投稿相關事務聯絡人：銘傳大學觀光學院休閒遊憩管理學系林<br> 佳陞老師(03)3507001分機3637</div></div>","attachments":[]}}