{"updateAt":"2022-02-18T01:49:08.150Z","data":{"category":"校內訊息公告區","title":"110學年度第1學期補考成績公佈","href":"http://www.smhs.kh.edu.tw/p/406-1000-2856,r24.php?Lang=zh-tw","date":"2022-02-08","external":false,"content":"<div><div></div><div><ul><li><h3><span><span>110學年度第1學期補考成績，請同學自行登入本校校務行政系統查閱。</span></span></h3></ul><h4><span><span>※<span><span>校務行政系統網址：</span></span><span><strong><a href=http://highschool.kh.edu.tw/Login.action><span><span>http://highschool.kh.edu.tw/Login.action</span></span></a></strong></span><span></span></span></span></h4><ul><li><h3><span><span>注意事項：成績公佈之日起<span>10日</span>內，提出申請查詢，</span> <span>逾期不予受理。</span></span></h3></ul><p> <p><span><span>註冊組</span><span>111/02/08</span></span></div></div>","attachments":[]}}