{"updateAt":"2022-04-05T04:49:31.401Z","data":{"category":"競賽活動公告區","title":"「創意圓夢‧公益行動計畫」","href":"http://www.smhs.kh.edu.tw/p/406-1000-3323,r21.php?Lang=zh-tw","date":"2022-03-31","external":false,"content":"<div><div></div><div>一、為鼓勵青少年發揮創意，結合公益組織規劃服務行動方<br> 案，透過回饋社會的行動，讓青少年能量與社會接軌，並<br> 創造青少年的正向自我價值，故辦理「創意圓夢‧公益行<br> 動」計畫。活動徵件自即日起至111年5月22日（星期日）<br> 止，開放24歲以下(或26歲以下的身心障礙者)對象個人或<br> 組隊報名，提出以高雄在地議題或社區需求為發想之行動<br> 方案，經審查核准後可補助個人最高3萬元，團體最高9萬<br> 元，詳情請見報名表簡章或上網查詢（網址：<br> https://reurl.cc/veZRqA ）。<br> 二、本計畫預定111年5月28日（星期六）於高雄市政府社會局<br> 婦幼青少年活動中心8號基地（高雄市鳳山區光復路二段<br> 120號1樓）辦理提案面審會議，請報名者預留時間親自出<br> 席簡報。<br> 三、相關訊息請上Facebook粉絲專頁「青瘋俠」或來電<br> (07)746-6900分機300青少年組洽詢。</div></div>","attachments":[]}}