{"updateAt":"2022-05-30T08:50:51.522Z","data":{"category":"競賽活動公告區","title":"「國立陽明交通大學創客電機 營」","href":"http://www.smhs.kh.edu.tw/p/406-1000-3791,r21.php?Lang=zh-tw","date":"2022-05-30","external":false,"content":"<div><div></div><div>國立陽明交通大學<br> 二、營隊宗旨：1. 引導學員學習 Maker 基本概念與工具，入<br> 門程式及 Arduino 開發板。2. 透過基礎課程、專案實作<br> 與黑客松競賽的歷程，讓學員體驗 Maker DIY生活。3. 使<br> 學員有機會將腦中想法，化為實際行動與成果，激發學員<br> 的創客精神。4. 經營創客俱樂部社群，讓有興趣的學員，<br> 擁有資源與動力，於營隊後持續實踐。<br> 三、活動日期：111 年 8 月 1 日(一) ~ 111 年 8 月 4 日<br> (四)。<br> 四、營隊地點：國立陽明交通大學光復校區 (新竹市大學路<br> 1001 號)。<br> 五、招收對象、人數：全國高中職學生，對創客、 電機、資工<br> 領域有興趣者， 40 人為限。<br> 六、報名資訊：111 年 4 月 30 日~111 年 6 月 12 日報名、<br> 111 年 6 月 19 日公告正取名單、111 年 6 月 19 日<br> ~111 年 6 月 25 日繳費。<br> 七、報名網址： https://forms.gle/T9KgVZ4iHMm7eoD76。</div></div>","attachments":[]}}