{"at":"2021-10-28T12:51:42.674Z","data":{"title":"「2021全國二足機器人競賽」及「國際新創機器人節合作競賽」","content":"\n\t\t國立臺灣師範大學機電工程學系於110年11月20日(星期六)舉辦「2021全國二足機器人競賽」及「國際新創機器人節合作競賽」，歡迎有興趣同學踴躍參加。\n說明：\n一、為培養大專及高中職(含)以下學校智慧型機器人科技人才，提昇科學教育及實踐機械、電機、電子、資訊等相關領域之技術整合能力，特辦理智慧型二足機器人競賽。\n二、本活動報名自即日起至110年11月5日(星期五)止，且於10月29日(星期五)前完成報名與繳費，即享有早鳥優惠報名費8折。詳細內容與報名訊息，請連結至本校機電工程學系網站查詢(http://www.me.ntnu.edu.tw/)。\n三、如有疑問，請逕洽本校機電工程學系楊智翔先生，電話：（02）77493503，電子信箱sean98789@ntnu.edu.tw。\n   ","contentHTML":"\n\t\t國立臺灣師範大學機電工程學系於110年11月20日(星期六)舉辦「2021全國二足機器人競賽」及「國際新創機器人節合作競賽」，歡迎有興趣同學踴躍參加。<br>\n說明：<br>\n一、為培養大專及高中職(含)以下學校智慧型機器人科技人才，提昇科學教育及實踐機械、電機、電子、資訊等相關領域之技術整合能力，特辦理智慧型二足機器人競賽。<br>\n二、本活動報名自即日起至110年11月5日(星期五)止，且於10月29日(星期五)前完成報名與繳費，即享有早鳥優惠報名費8折。詳細內容與報名訊息，請連結至本校機電工程學系網站查詢(http://www.me.ntnu.edu.tw/)。<br>\n三、如有疑問，請逕洽本校機電工程學系楊智翔先生，電話：（02）77493503，電子信箱sean98789@ntnu.edu.tw。\n   ","attachments":[],"extra":{}}}