{"at":"2021-09-29T01:28:23.435Z","data":{"title":"轉知「台灣教育研究學會2021國際學術研討會」(TERA 2021)","content":"\n\t\t國立中山大學教育研究所、台灣教育研究學會訂於110年11月12日(星期五)至13日(星期六)舉辦「台灣教育研究學會2021國際學術研討會」(TERA 2021)，為廣邀各教育先進共襄盛\n舉，故延長截稿日至10月3日(星期日)止，相關資訊如下：\n一、旨揭研討會因應新冠肺炎(COVID-19)疫情，將採線上視訊方式辦理。\n二、各項重要時程如下：\n(一)摘要延長截稿日期：110年10月3日(星期日)。\n(二)摘要審查通知日期：110年10月13日(星期三)。\n(三)Main Conference：110年11月12日(星期五)至13日(星期六)。\n(四)論文發表方式：口頭發表、壁報發表，可用中英文發表。\n(五)會議地點：國立中山大學(高雄市鼓山區蓮海路70號)。\n(六)報名詳情請參閱研討會網站： https://tera2021.nsysu.edu.tw/ 。\n   ","contentHTML":"\n\t\t國立中山大學教育研究所、台灣教育研究學會訂於110年11月12日(星期五)至13日(星期六)舉辦「台灣教育研究學會2021國際學術研討會」(TERA 2021)，為廣邀各教育先進共襄盛<br>\n舉，故延長截稿日至10月3日(星期日)止，相關資訊如下：<br>\n一、旨揭研討會因應新冠肺炎(COVID-19)疫情，將採線上視訊方式辦理。<br>\n二、各項重要時程如下：<br>\n(一)摘要延長截稿日期：110年10月3日(星期日)。<br>\n(二)摘要審查通知日期：110年10月13日(星期三)。<br>\n(三)Main Conference：110年11月12日(星期五)至13日(星期六)。<br>\n(四)論文發表方式：口頭發表、壁報發表，可用中英文發表。<br>\n(五)會議地點：國立中山大學(高雄市鼓山區蓮海路70號)。<br>\n(六)報名詳情請參閱研討會網站： https://tera2021.nsysu.edu.tw/ 。\n   ","attachments":[{"name":"33450321_1102500491_ATT1.jpg(另開新視窗)","url":"http://www.smhs.kh.edu.tw/var/file/0/1000/attach/54/pta_1411_7027435_14316.jpg"}],"extra":{}}}