{"at":"2021-11-04T12:51:40.067Z","data":{"title":"轉知「特斯拉電動車技術研習與ADAS體驗活動」","content":"\n\t\t健行學校財團法人健行科技大學辦理高教深耕計畫之「特斯拉電動車技術研習與ADAS體驗活動」，資訊如下：\n一、本研習課程大綱：1.介紹特斯拉電動車電控、電池與電機之作用、2.體驗電動車ADAS先進駕駛輔助系統、3.各種功能體驗與操作。\n二、研習時間：2021年11月12日 09:00~13:00 共4小時(全程參與者研習結束核發4小時研習時數)，研習教室：汽車修護工廠K101(本校工學院一館大樓後方)，講師：彭志良 大城\n輪胎機械股份有限公司 執行長，費用：免費(提供午餐便當)，全國教師在職進修網課程代碼： 3273528，報名時間：即日起至2021年11月10日止，報名網址如下或請掃瞄附件QR code\nhttps://www1.inservice.edu.tw/Script/CourseView.aspx?CourseId=3273528。\n   ","contentHTML":"\n\t\t健行學校財團法人健行科技大學辦理高教深耕計畫之「特斯拉電動車技術研習與ADAS體驗活動」，資訊如下：<br>\n一、本研習課程大綱：1.介紹特斯拉電動車電控、電池與電機之作用、2.體驗電動車ADAS先進駕駛輔助系統、3.各種功能體驗與操作。<br>\n二、研習時間：2021年11月12日 09:00~13:00 共4小時(全程參與者研習結束核發4小時研習時數)，研習教室：汽車修護工廠K101(本校工學院一館大樓後方)，講師：彭志良 大城<br>\n輪胎機械股份有限公司 執行長，費用：免費(提供午餐便當)，全國教師在職進修網課程代碼： 3273528，報名時間：即日起至2021年11月10日止，報名網址如下或請掃瞄附件QR code<br>\nhttps://www1.inservice.edu.tw/Script/CourseView.aspx?CourseId=3273528。\n   ","attachments":[{"name":"33751684_1100011326_ATT1.pdf(另開新視窗)","url":"http://www.smhs.kh.edu.tw/var/file/0/1000/attach/22/pta_1771_6879899_16559.pdf"}],"extra":{}}}