{"at":"2021-08-30T12:52:58.621Z","data":{"title":"轉知「Workshop：Holocaust Education & Practice of Yad Vashem online resources on Teaching」","content":"\n\t\t教育部國民及學前教育署人權教育資源中心辦理「Workshop：Holocaust Education & Practice of Yad Vashem online resources on Teaching」，相關資訊請參閱附件。\n   ","contentHTML":"\n\t\t教育部國民及學前教育署人權教育資源中心辦理「Workshop：Holocaust Education &amp; Practice of Yad Vashem online resources on Teaching」，相關資訊請參閱附件。\n   ","attachments":[{"name":"33196716_1100007083_ATT1.pdf(另開新視窗)","url":"http://www.smhs.kh.edu.tw/var/file/0/1000/attach/83/pta_1088_2303644_13546.pdf"}],"extra":{}}}