{"at":"2021-10-21T08:38:26.754Z","data":{"title":"高雄市立瑞祥辦理110學年度高中職跨域自主學習線上課程","content":"\n\t\t說明：\n一、依據民國110年7月19日臺教授國部字第1100084553A號函辦理。\n二、課程名稱：簡單機械。\n三、講師：臺北市立景興國中郭智嘉老師。\n四、活動時間：110年11月6日（六）上午08：00─12：00。\n五、活動地點：採線上辦理，使用Google Meet線上會議、Seesaw教學互動平台。\n六、參加對象：國中及高一學生。\n七、活動目的：應用線上平台，以雙語教學模式引導「簡單機械」單元主題學習，\n       培養學生跨域自主學習與科技應用整合的能力。\n八、課程內容：Seesaw平台使用教學、簡單機械原理、互動與問答等。\n九、報名方式：即日起至110年10月30日（六）止，完成 Google表單報名\n       資料填寫（https://forms.gle/mGFgCnqo7NbhG7HK9）。\n   ","contentHTML":"\n\t\t說明：<br>\n一、依據民國110年7月19日臺教授國部字第1100084553A號函辦理。<br>\n二、課程名稱：簡單機械。<br>\n三、講師：臺北市立景興國中郭智嘉老師。<br>\n四、活動時間：110年11月6日（六）上午08：00─12：00。<br>\n五、活動地點：採線上辦理，使用Google Meet線上會議、Seesaw教學互動平台。<br>\n六、參加對象：國中及高一學生。<br>\n七、活動目的：應用線上平台，以雙語教學模式引導「簡單機械」單元主題學習，<br>\n       培養學生跨域自主學習與科技應用整合的能力。<br>\n八、課程內容：Seesaw平台使用教學、簡單機械原理、互動與問答等。<br>\n九、報名方式：即日起至110年10月30日（六）止，完成 Google表單報名<br>\n       資料填寫（https://forms.gle/mGFgCnqo7NbhG7HK9）。\n   ","attachments":[],"extra":{}}}