{"at":"2021-11-01T04:45:07.583Z","data":{"title":"公告 110優質學習環境佈置比賽得獎班級","content":"\n\t\t請得獎班級派員至訓育組簽領獎金。\n\n\n\n\n\n\n\n班級\n名次\n\n\n109\n1\n\n\n102\n2\n\n\n103\n3\n\n\n203\n1\n\n\n207\n2\n\n\n206\n3\n\n\n\n \n\n   ","contentHTML":"\n\t\t<p><span style=\"font-size: 2.25em; color: rgb(255, 0, 0);\">請得獎班級派員至訓育組簽領獎金。</span></p>\n<table border=\"0\" cellpadding=\"0\" cellspacing=\"0\" style=\"border-collapse:collapse;width:278px;\" width=\"276\">\n<colgroup>\n<col style=\"width: 171px; text-align: center;\">\n<col style=\"width: 107px; text-align: center;\">\n</colgroup>\n<tbody>\n<tr height=\"40\" style=\"height:40px;\">\n<td height=\"40\" style=\"height: 40px; width: 171px; text-align: center;\"><span style=\"font-size:2.25em;\">班級</span></td>\n<td style=\"border-left: none; width: 107px; text-align: center;\"><span style=\"font-size:2.25em;\">名次</span></td>\n</tr>\n<tr height=\"61\" style=\"height:61px;\">\n<td height=\"61\" style=\"height: 61px; text-align: center;\"><span style=\"font-size:2.25em;\">109</span></td>\n<td style=\"border-left: none; width: 107px; text-align: center;\"><span style=\"font-size:2.25em;\">1</span></td>\n</tr>\n<tr height=\"61\" style=\"height:61px;\">\n<td height=\"61\" style=\"height: 61px; border-top: none; text-align: center;\"><span style=\"font-size:2.25em;\">102</span></td>\n<td style=\"border-top: none; border-left: none; width: 107px; text-align: center;\"><span style=\"font-size:2.25em;\">2</span></td>\n</tr>\n<tr height=\"61\" style=\"height:61px;\">\n<td height=\"61\" style=\"height: 61px; border-top: none; text-align: center;\"><span style=\"font-size:2.25em;\">103</span></td>\n<td style=\"border-top: none; border-left: none; width: 107px; text-align: center;\"><span style=\"font-size:2.25em;\">3</span></td>\n</tr>\n<tr height=\"61\" style=\"height:61px;\">\n<td height=\"61\" style=\"height: 61px; border-top: none; text-align: center;\"><span style=\"font-size:2.25em;\">203</span></td>\n<td style=\"border-top: none; border-left: none; width: 107px; text-align: center;\"><span style=\"font-size:2.25em;\">1</span></td>\n</tr>\n<tr height=\"61\" style=\"height:61px;\">\n<td height=\"61\" style=\"height: 61px; border-top: none; text-align: center;\"><span style=\"font-size:2.25em;\">207</span></td>\n<td style=\"border-top: none; border-left: none; width: 107px; text-align: center;\"><span style=\"font-size:2.25em;\">2</span></td>\n</tr>\n<tr height=\"61\" style=\"height:61px;\">\n<td height=\"61\" style=\"height: 61px; border-top: none; text-align: center;\"><span style=\"font-size:2.25em;\">206</span></td>\n<td style=\"border-top: none; border-left: none; width: 107px; text-align: center;\"><span style=\"font-size:2.25em;\">3</span></td>\n</tr>\n</tbody>\n</table>\n<p>&nbsp;</p>\n\n   ","attachments":[],"extra":{}}}