{"at":"2021-11-23T08:38:59.776Z","data":{"title":"110學年度上學期第二次期中考各科試卷難易度及題項配分表","content":"\n\t\t110學年度上學期第二次期中考各科試卷難易度及題項配分表，請參閱附件。\n   ","contentHTML":"\n\t\t110學年度上學期第二次期中考各科試卷難易度及題項配分表，請參閱附件。\n   ","attachments":[{"name":"110-1第2次期中考各科題項及配分表(高一).pdf(另開新視窗)","url":"http://www.smhs.kh.edu.tw/var/file/0/1000/attach/87/pta_1928_2599671_69148.pdf"},{"name":"110-1第2次期中考各科題項及配分表(高二).pdf(另開新視窗)","url":"http://www.smhs.kh.edu.tw/var/file/0/1000/attach/87/pta_1929_4513508_69148.pdf"},{"name":"110-1第2次期中考各科題項及配分表(高三).pdf(另開新視窗)","url":"http://www.smhs.kh.edu.tw/var/file/0/1000/attach/87/pta_1930_9193934_69148.pdf"}],"extra":{}}}