{"at":"2021-08-13T08:37:18.685Z","data":{"title":"轉知公務人員應專門職業及技術人員考試錄取或及格，參加取得執業資格之相關訓練，業經考試院會同行政院認定為得 申請留職停薪之情事。","content":"\n\t\t相關內容請參見附件。\n   ","contentHTML":"\n\t\t相關內容請參見附件。\n   ","attachments":[{"name":"高市府人力字第11030630900號.pdf(另開新視窗)","url":"http://www.smhs.kh.edu.tw/var/file/0/1000/attach/84/pta_958_4221929_38241.pdf"},{"name":"部銓四字第1105364648號.pdf(另開新視窗)","url":"http://www.smhs.kh.edu.tw/var/file/0/1000/attach/84/pta_959_8631554_38241.pdf"},{"name":"考臺組貳一字第11000043021號.pdf(另開新視窗)","url":"http://www.smhs.kh.edu.tw/var/file/0/1000/attach/84/pta_960_2838613_38241.pdf"}],"extra":{}}}