{"at":"2021-09-03T08:37:49.949Z","data":{"title":"訂定「高雄市政府員工酒後駕車行政責任處理原則」","content":"\n\t\t一、重申為貫徹本府杜絕酒後駕車，建立酒駕零容忍之決心，訂定「高雄市政府員工酒後駕車行政責任處理原則」，業經本府110年2月2日第511次市政會議審議通過。\n二、檢附「高雄市政府員工酒後駕車行政責任處理原則」、總說明及逐點說明供參。\n   ","contentHTML":"\n\t\t一、重申為貫徹本府杜絕酒後駕車，建立酒駕零容忍之決心，訂定「高雄市政府員工酒後駕車行政責任處理原則」，業經本府110年2月2日第511次市政會議審議通過。<br>\n二、檢附「高雄市政府員工酒後駕車行政責任處理原則」、總說明及逐點說明供參。\n   ","attachments":[{"name":"訂定「高雄市政府員工酒後駕車行政責任處理原則」府函1100209.pdf(另開新視窗)","url":"http://www.smhs.kh.edu.tw/var/file/0/1000/attach/16/pta_1118_2225111_32977.pdf"},{"name":"高雄市政府員工酒後駕車行政責任處理原則1100209.pdf(另開新視窗)","url":"http://www.smhs.kh.edu.tw/var/file/0/1000/attach/16/pta_1119_792791_32978.pdf"},{"name":"高雄市政府員工酒後駕車行政責任處理原則說明1100209.pdf(另開新視窗)","url":"http://www.smhs.kh.edu.tw/var/file/0/1000/attach/16/pta_1120_6581544_32978.pdf"},{"name":"高雄市政府員工酒後駕車行政責任處理原則總說明1100209.pdf(另開新視窗)","url":"http://www.smhs.kh.edu.tw/var/file/0/1000/attach/16/pta_1121_6695912_32978.pdf"}],"extra":{}}}